bus_mgmt_dolt_mcp_server/bus_mgmt_dolt_mcp_server.py
bus_mgmt_dolt_mcp_server-0.1.23.dist-info/METADATA
bus_mgmt_dolt_mcp_server-0.1.23.dist-info/WHEEL
bus_mgmt_dolt_mcp_server-0.1.23.dist-info/entry_points.txt
bus_mgmt_dolt_mcp_server-0.1.23.dist-info/top_level.txt
bus_mgmt_dolt_mcp_server-0.1.23.dist-info/RECORD
