Metadata-Version: 2.4
Name: bus-mgmt-dolt-mcp-server
Version: 0.1.23
Summary: Bus Management Dolt MCP Server
Requires-Python: >=3.11
Requires-Dist: fastmcp
Requires-Dist: requests
Requires-Dist: argparse
